[
  {
    "id": 1778350398998,
    "name": "ujjwal",
    "phone": "1231231231",
    "email": "123@gmail.com",
    "message": "123321",
    "date": "09 May 2026",
    "time": "11:43 pm",
    "status": "Pending"
  },
  {
    "id": 1778167032937,
    "name": "SAANVI",
    "phone": "1231231233",
    "email": "123@gmail.com",
    "message": "LOOSE MOTION",
    "date": "07 May 2026",
    "time": "08:47 pm",
    "status": "Confirmed"
  },
  {
    "id": 1778166625378,
    "name": "saanvi",
    "phone": "1231231233",
    "email": "123@gmail.com",
    "message": "na",
    "date": "07 May 2026",
    "time": "08:40 pm",
    "status": "Completed"
  },
  {
    "id": 1777911669897,
    "name": "123",
    "phone": "1231231233",
    "email": "123@gmail.com",
    "message": "eqweqw",
    "date": "04 May 2026",
    "time": "09:51 pm",
    "status": "Pending"
  },
  {
    "id": 1777833186850,
    "name": "saanvi",
    "phone": "1231231233",
    "email": "123@gmail.com",
    "message": "123123123",
    "date": "04 May 2026",
    "time": "12:03 am",
    "status": "Pending"
  },
  {
    "id": 1777797705575,
    "name": "Test Patient",
    "phone": "9876543210",
    "email": "test@gmail.com",
    "message": "Test appointment",
    "date": "03 May 2026",
    "time": "02:11 pm",
    "status": "Pending"
  }
]